continuous_peak_fit-0.0.1.data/scripts/CPF_XRD_FitPattern
continuous_peak_fit-0.0.1.data/scripts/CPF_generate_inputs
cpf/DioptasFunctions.py
cpf/GSASIIFunctions.py
cpf/ImageMetaData.py
cpf/Mca.py
cpf/Med.py
cpf/MedFunctions.py
cpf/PeakFunctions.py
cpf/Plot85Functions.py
cpf/WriteDifferentialStrain.py
cpf/WriteMultiFit.py
cpf/WritePolydefix.py
cpf/WritePolydefixED.py
cpf/XRD_FitPattern.py
cpf/XRD_FitSubpattern.py
cpf/__init__.py
continuous_peak_fit-0.0.1.dist-info/LICENSE.txt
continuous_peak_fit-0.0.1.dist-info/METADATA
continuous_peak_fit-0.0.1.dist-info/WHEEL
continuous_peak_fit-0.0.1.dist-info/top_level.txt
continuous_peak_fit-0.0.1.dist-info/RECORD
