Metadata-Version: 2.1
Name: continuous-peak-fit
Version: 0.0.1
Summary: Fits azimuth/time dependency of peaks with Fourier Series descriptions
Home-page: https://github.com/ExperimentalMineralPhysics/Continuous-Peak-Fit
Author: Simon Hunt & Danielle Fenech
Author-email: simon.hunt@manchester.ac.uk
License: UNKNOWN
Platform: UNKNOWN
Classifier: Programming Language :: Python :: 3
Classifier: License :: OSI Approved :: MIT License
Classifier: Operating System :: OS Independent
Requires-Python: >=3.6
Requires-Dist: matplotlib
Requires-Dist: pycairo
Requires-Dist: lmfit
Requires-Dist: h5py
Requires-Dist: pillow
Requires-Dist: pyFAI
